README
setup.py
linux_daemon/__init__.py
linux_daemon/linux_daemon.py
linux_daemon/signalhandler.py
linux_daemon.egg-info/PKG-INFO
linux_daemon.egg-info/SOURCES.txt
linux_daemon.egg-info/dependency_links.txt
linux_daemon.egg-info/requires.txt
linux_daemon.egg-info/top_level.txt