Metadata-Version: 1.1
Name: linux-daemon
Version: 0.1.6
Summary: A linux daemon wrapper
Home-page: http://www.victorclaessen.nl
Author: Victor Claessen
Author-email: victor@victorclaessen.nl
License: Free For Educational Use
Keywords: linux daemon framework wrapper
Platform: UNKNOWN
Classifier: Development Status :: 3 - Alpha
Classifier: Intended Audience :: Developers
Classifier: Topic :: Software Development :: Libraries :: Application Frameworks
Classifier: License :: Free For Educational Use
Classifier: Programming Language :: Python :: 2.7
